{
  "version": 1,
  "dependencies": [
    {
      "source": {
        "git": {
          "remote": "https://github.com/observatorium/api.git",
          "subdir": "jsonnet/lib"
        }
      },
      "version": "2adff5fcce97b775d9345e316a5d7ee8dff1737d",
      "sum": "/33386b3/boEQGuUF3y8mc7iOzFekzLuPtozDzTKfhs=",
      "name": "observatorium-api"
    },
    {
      "source": {
        "git": {
          "remote": "https://github.com/observatorium/observatorium.git",
          "subdir": "configuration"
        }
      },
      "version": "ddd91bbfa980f9588af7ad24fa6e33ae24cda852",
      "sum": "3JuzPRAtOLmV15ADRx9ylrUD+XlCeJzZjg0LrPIAF3c="
    },
    {
      "source": {
        "git": {
          "remote": "https://github.com/observatorium/thanos-receive-controller.git",
          "subdir": "jsonnet/lib"
        }
      },
      "version": "cd12a419fc00eeb354d1f48e3077648222b16c07",
      "sum": "0yZzNAcHQER0vE90d4iur3mYSitIhe8DhIFBeWdlb6k=",
      "name": "thanos-receive-controller"
    },
    {
      "source": {
        "git": {
          "remote": "https://github.com/observatorium/up.git",
          "subdir": "jsonnet"
        }
      },
      "version": "21b9125fa700ce2f2472caef720086179329b33e",
      "sum": "0FKabnXd0rMeu8YpkkopEOknqBf5PLq/DIIDd0ve7cU=",
      "name": "up"
    },
    {
      "source": {
        "git": {
          "remote": "https://github.com/thanos-io/kube-thanos.git",
          "subdir": "jsonnet/kube-thanos"
        }
      },
      "version": "33ac381e9594865895fa4a2e7c08d8a3fafa62cd",
      "sum": "7GtJlZ7j+ZODa4KKLTsryq0DKZ+hTMJLqaiDQ6jjYOI="
    }
  ],
  "legacyImports": false
}
